{"name":"高可用","slug":"高可用","count":1,"postlist":[{"title":"中间件高可用知识点","uid":"33521bd94ee66cdecae1afca83643ee9","slug":"中间件高可用知识点","date":"2021-05-03T20:47:18.000Z","updated":"2022-09-15T14:22:17.560Z","comments":true,"path":"api/articles/中间件高可用知识点.json","keywords":null,"cover":null,"text":"不同中间件的高可用架构RabbitMQ高可用 RabbitMQ 是比较有代表性的，因为是基于主从（非分布式）做高可用性的，我们就以 RabbitMQ 为例子讲解第一种 MQ 的高可用性怎么实现 RabbitMQ 有三种模式：单机模式、普通集群模式、镜像集群模式。 单机模式，就是 ...","link":"","photos":[],"count_time":{"symbolsCount":"6.3k","symbolsTime":"6 mins."},"categories":[],"tags":[{"name":"系统设计","slug":"系统设计","count":2,"path":"api/tags/系统设计.json"},{"name":"高可用","slug":"高可用","count":1,"path":"api/tags/高可用.json"}],"author":{"name":"谢华客","slug":"blog-author","avatar":"https://img-blog.csdnimg.cn/20210313122054101.png","link":"/","description":"记录一些笔记和心情的地方","socials":{"github":"https://github.com/stephentse9527","twitter":"","stackoverflow":"","wechat":"","qq":"","weibo":"","zhihu":"","csdn":"","juejin":"","customs":{}}}}]}